{
    manifest:
    {
        "library.cf": { description: "Design Center stdlib" },
        "test.pl": { test:true },
        "README.md": { documentation: true }
    },

    metadata:
    {
        name: "CFEngine::dclib::3.5.0",
	    description: "Design Center standard library for CFEngine 3.5.0 and higher",
        version: "3.5.0",
        license: "MIT",
        tags: [ "cfdc", "stdlib" ],
        authors: [ "CFEngine AS" ],
        depends: { "cfengine": { "version": "3.5.0" } }
    },

    namespace: "cfdc_dclib_350",
    interface: [ "library.cf" ]
}
