{
   "activated" : true,
   "wp_params" : {
     "DB_NAME" : "wordpress_db",
     "DB_USER" : "wordpress_user",
     "DB_PASSWORD" : "wordpress_pass"
   },
   "bycontext" : {
     "debian": {
       "htmlroot" : "/var/www",
       "wp_dir" : "/var/www/wordpress",
       "packages" : [
         "apache2", 
         "php5",
         "php5-mysql",
         "mysql-server"
       ],
       "mysql_process" : "/usr/sbin/mysqld",
       "httpd_process" : "/usr/sbin/apache2",
       "service_cmd" : "/usr/sbin/service",
       "apache_srv" : "apache2",
     },
     "redhat": {
       "htmlroot" : "/var/www/html",
       "wp_dir" : "/var/www/html/wordpress",
       "packages" : [
         "httpd",
         "php",
         "php-mysql",
         "mysql-server"
       ],
       "mysql_process" : "^mysqld",
       "httpd_process" : "^httpd",
       "service_cmd" : "/sbin/service",
       "apache_srv" : "httpd",
     },
     "any" : {
       "mysql_srv" : "httpd",
     }
   }
}

