{
    manifest:
    {
        "main.cf": { description: "main file", version: 1.2 },
        "README.md": { documentation: true },
        "test.pl": { test:true },
        changelog: { description: "changelog" },
        "params/example.json": { },
    },

    metadata:
    {
        name: "Security::security_limits",
	    description: "Configure /etc/security/limits.conf",
        version: 1.2,
        license: "MIT",
        tags: [ "cfdc" ],
        authors: [ "Nick Anderson <nick@cmdln.org>", "Ted Zlatanov <tzz@lifelogs.com>" ],
        depends: { "CFEngine::dclib": {}, cfengine: {version: "3.4.0"}, os: [ "linux" ] },
    },

    api:
    {
        // the key is the name of the bundle!
        limits:
        [
            { type: "environment", name: "runenv", },
            { type: "metadata", name: "metadata", },
            { type: "string", name: "filename", default: "/etc/security/limits.conf" },
            { type: "array", name: "domains" },
            { type: "boolean", name: "empty_first", default: true, },
            { type: "boolean", name: "ensure_absent", default: false, },
            { type: "return", name: "filename", },
        ],
    },

    namespace: "cfdc_security",
    
    interface: [ "main.cf" ],
}
