{
    manifest:
    {
        "main.cf": { desc: "main file" },
        "test.pl": {test:true},
        "README.md": { documentation: true },
        "README.include": { documentation: true },
        "params/demo.json": { comment: "simple demo of Cloud::Autobalance: AWS EC2 and OpenStack" },
        "params/demo_vmware.json": { comment: "simple demo of Cloud::Autobalance: VMWare and OpenStack" },
    },

    metadata:
    {
        name: "Cloud::Autobalance",
	    description: "Autobalance load amongst cloud offerings based on Data::Classes results.",
        version: 1.0,
        license: "MIT",
        tags: [ "cfdc", "cloud", "balance", "ec2", "openstack" ],
        authors: [ "Ted Zlatanov <tzz@lifelogs.com>" ],
        depends: { "Cloud::Services::VMWare": {}, "Cloud::Services::OpenStack": {}, "Cloud::Services::AWS::EC2": {}, "Data::Classes": { }, cfengine: { version: "3.5.0" } }
    },
    
    api:
    {
        autobalance:
        [
            { type: "environment", name: "runenv", },
            { type: "metadata", name: "mymetadata", },
            { type: "string", name: "url", description: "URL to check for threshold string", validation: "URL" },
            { type: "string", name: "collector", description: "Program to collect the URL contents", default: "/usr/bin/curl -s" },
            { type: "array", name: "thresholds", description: "Threshold definitions" },
            { type: "list", name: "ec2_options", description: "EC2 options" },
            { type: "list", name: "openstack_options", description: "OpenStack options" },
            { type: "list", name: "vmware_options", description: "VMWare options" },
            { type: "array", name: "common_options", description: "Common options for all sketches" },
        ],
    },

    namespace: "cfdc_cloud",
    interface: [ "main.cf" ]
}
